forwarding_bot/__init__.py
forwarding_bot/__main__.py
forwarding_bot/__version__.py
forwarding_bot/settings.py
forwarding_bot/arguments/__init__.py
forwarding_bot/arguments/_parser.py
forwarding_bot/arguments/models.py
forwarding_bot/config/__init__.py
forwarding_bot/config/_data.py
forwarding_bot/imports/__init__.py
forwarding_bot/imports/_json.py
forwarding_bot/vk/__init__.py
forwarding_bot/vk/_bot.py
forwarding_bot/vk/_middleware.py
forwarding_bot/vk/_blueprint/__init__.py
forwarding_bot/vk/_blueprint/attachment_handler.py
forwarding_bot/vk/_blueprint/blueprint.py
forwarding_bot/vk/_blueprint/message_helper.py
forwarding_bot/vk/_blueprint/nested_handler.py
forwarding_bot-2.5.2.dist-info/LICENSE
forwarding_bot-2.5.2.dist-info/METADATA
forwarding_bot-2.5.2.dist-info/WHEEL
forwarding_bot-2.5.2.dist-info/dependency_links.txt
forwarding_bot-2.5.2.dist-info/entry_points.txt
forwarding_bot-2.5.2.dist-info/top_level.txt
forwarding_bot-2.5.2.dist-info/RECORD
