Metadata-Version: 2.1
Name: forwarding-bot
Version: 2.5.2
Summary: UNKNOWN
Home-page: https://github.com/dhvcc/forwarding-bot
Author: Alexey Artishevskiy
Author-email: 1337kwiz@gmail.com
License: UNKNOWN
Project-URL: Source, https://github.com/dhvcc/forwarding-bot
Project-URL: Documentation, https://github.com/dhvcc/forwarding-bot#documentation
Project-URL: Tracker, https://github.com/dhvcc/forwarding-bot/issues
Platform: UNKNOWN
Classifier: Natural Language :: English
Classifier: Natural Language :: Russian
Classifier: Intended Audience :: Developers
Classifier: Intended Audience :: End Users/Desktop
Classifier: License :: OSI Approved :: MIT License
Classifier: Typing :: Typed
Classifier: Development Status :: 5 - Production/Stable
Classifier: Operating System :: OS Independent
Classifier: Programming Language :: Python :: 3.7
Classifier: Programming Language :: Python :: 3.8
Requires-Python: >=3.7
Requires-Dist: vkbottle (==v2.7.12)
Requires-Dist: aiogram
Requires-Dist: aiohttp
Requires-Dist: pytz
Provides-Extra: dev
Requires-Dist: pre-commit ; extra == 'dev'
Requires-Dist: flake8 ; extra == 'dev'
Requires-Dist: autoflake ; extra == 'dev'
Requires-Dist: autopep8 ; extra == 'dev'
Requires-Dist: pyupgrade ; extra == 'dev'
Provides-Extra: speedups
Requires-Dist: aiohttp[speedups] ; extra == 'speedups'
Requires-Dist: uvloop ; extra == 'speedups'
Requires-Dist: ujson ; extra == 'speedups'
